{
	"metaData": {
		"Raw data ID": "IMG_C_A2_23_202266.jpg",
		"copyrighter": "㈜미소정보기술",
		"resolution": "1920X1080",
		"date": "2021-12-15",
		"breed": "코리안숏헤어",
		"age": "10",
		"gender": "F",
		"region": "L",
		"camera type": "IMG",
		"species": "C",
		"lesions": "A2",
		"diagnosis": "",
		"Path": "유증상",
		"identifier": "피부질환",
		"src_path": "/라벨링데이터/반려묘/피부/일반카메라/유증상/A2_비듬_각질_상피성잔고리",
		"label_path": "/라벨링데이터/반려묘/피부/일반카메라/유증상/A2_비듬_각질_상피성잔고리",
		"type": "json",
		"fileformat": "jpg"
	},
	"inspRejectYn": "N",
	"labelingInfo": [
		{
			"polygon": {
				"color": "#1beaac",
				"location": [
					{
						"x1": 1454,
						"y1": 573,
						"x2": 1533,
						"y2": 559,
						"x3": 1573,
						"y3": 544,
						"x4": 1623,
						"y4": 514,
						"x5": 1632,
						"y5": 492,
						"x6": 1619,
						"y6": 450,
						"x7": 1590,
						"y7": 410,
						"x8": 1563,
						"y8": 378,
						"x9": 1545,
						"y9": 370,
						"x10": 1480,
						"y10": 383,
						"x11": 1428,
						"y11": 422,
						"x12": 1385,
						"y12": 443,
						"x13": 1338,
						"y13": 460,
						"x14": 1278,
						"y14": 478,
						"x15": 1253,
						"y15": 487,
						"x16": 1238,
						"y16": 487,
						"x17": 1223,
						"y17": 465,
						"x18": 1227,
						"y18": 453,
						"x19": 1258,
						"y19": 444,
						"x20": 1299,
						"y20": 422,
						"x21": 1397,
						"y21": 390,
						"x22": 1450,
						"y22": 377,
						"x23": 1470,
						"y23": 369,
						"x24": 1493,
						"y24": 348,
						"x25": 1488,
						"y25": 298,
						"x26": 1469,
						"y26": 275,
						"x27": 1388,
						"y27": 277,
						"x28": 1239,
						"y28": 347,
						"x29": 1174,
						"y29": 392,
						"x30": 1162,
						"y30": 440,
						"x31": 1162,
						"y31": 485,
						"x32": 1177,
						"y32": 528,
						"x33": 1207,
						"y33": 552,
						"x34": 1257,
						"y34": 577,
						"x35": 1318,
						"y35": 583,
						"x36": 1454,
						"y36": 573
					}
				],
				"label": "A2_비듬_각질_상피성잔고리",
				"type": "polygon"
			}
		},
		{
			"box": {
				"color": "#1beaac",
				"location": [
					{
						"x": 1162,
						"y": 275,
						"width": 470,
						"height": 308
					}
				],
				"label": "A2_비듬_각질_상피성잔고리",
				"type": "box"
			}
		}
	]
}