{
	"metaData": {
		"Raw data ID": "IMG_C_A2_38_202471.jpg",
		"copyrighter": "㈜미소정보기술",
		"resolution": "1920X1080",
		"date": "2021-12-15",
		"breed": "러시안블루",
		"age": "10",
		"gender": "F",
		"region": "L",
		"camera type": "IMG",
		"species": "C",
		"lesions": "A2",
		"diagnosis": "",
		"Path": "유증상",
		"identifier": "피부질환",
		"src_path": "/라벨링데이터/반려묘/피부/일반카메라/유증상/A2_비듬_각질_상피성잔고리",
		"label_path": "/라벨링데이터/반려묘/피부/일반카메라/유증상/A2_비듬_각질_상피성잔고리",
		"type": "json",
		"fileformat": "jpg"
	},
	"inspRejectYn": "N",
	"labelingInfo": [
		{
			"polygon": {
				"color": "#1beaac",
				"location": [
					{
						"x1": 614,
						"y1": 705,
						"x2": 700,
						"y2": 705,
						"x3": 747,
						"y3": 698,
						"x4": 794,
						"y4": 678,
						"x5": 805,
						"y5": 663,
						"x6": 804,
						"y6": 650,
						"x7": 774,
						"y7": 634,
						"x8": 675,
						"y8": 623,
						"x9": 622,
						"y9": 623,
						"x10": 578,
						"y10": 633,
						"x11": 563,
						"y11": 643,
						"x12": 552,
						"y12": 664,
						"x13": 555,
						"y13": 699,
						"x14": 565,
						"y14": 707,
						"x15": 565,
						"y15": 707,
						"x16": 567,
						"y16": 708,
						"x17": 614,
						"y17": 705
					}
				],
				"label": "A2_비듬_각질_상피성잔고리",
				"type": "polygon"
			}
		},
		{
			"box": {
				"color": "#1beaac",
				"location": [
					{
						"x": 552,
						"y": 623,
						"width": 253,
						"height": 85
					}
				],
				"label": "A2_비듬_각질_상피성잔고리",
				"type": "box"
			}
		}
	]
}