{
	"metaData": {
		"Raw data ID": "IMG_C_A2_201794.jpg",
		"copyrighter": "㈜미소정보기술",
		"resolution": "1920X1080",
		"date": "2021-12-15",
		"breed": "스코티쉬폴드",
		"age": "2",
		"gender": "F",
		"region": "H",
		"camera type": "IMG",
		"species": "C",
		"lesions": "A2",
		"diagnosis": "",
		"Path": "유증상",
		"identifier": "피부질환",
		"src_path": "/라벨링데이터/반려묘/피부/일반카메라/유증상/A2_비듬_각질_상피성잔고리",
		"label_path": "/라벨링데이터/반려묘/피부/일반카메라/유증상/A2_비듬_각질_상피성잔고리",
		"type": "json",
		"fileformat": "jpg"
	},
	"inspRejectYn": "N",
	"labelingInfo": [
		{
			"polygon": {
				"color": "#1beaac",
				"location": [
					{
						"x1": 1492,
						"y1": 827,
						"x2": 1544,
						"y2": 848,
						"x3": 1578,
						"y3": 852,
						"x4": 1648,
						"y4": 820,
						"x5": 1672,
						"y5": 798,
						"x6": 1672,
						"y6": 727,
						"x7": 1608,
						"y7": 670,
						"x8": 1514,
						"y8": 622,
						"x9": 1408,
						"y9": 583,
						"x10": 1294,
						"y10": 572,
						"x11": 1245,
						"y11": 577,
						"x12": 1182,
						"y12": 577,
						"x13": 1140,
						"y13": 583,
						"x14": 1114,
						"y14": 677,
						"x15": 1134,
						"y15": 717,
						"x16": 1153,
						"y16": 740,
						"x17": 1178,
						"y17": 775,
						"x18": 1204,
						"y18": 797,
						"x19": 1232,
						"y19": 802,
						"x20": 1254,
						"y20": 790,
						"x21": 1295,
						"y21": 788,
						"x22": 1320,
						"y22": 785,
						"x23": 1375,
						"y23": 789,
						"x24": 1428,
						"y24": 804,
						"x25": 1464,
						"y25": 825,
						"x26": 1492,
						"y26": 827
					}
				],
				"label": "A2_비듬_각질_상피성잔고리",
				"type": "polygon"
			}
		},
		{
			"box": {
				"color": "#1beaac",
				"location": [
					{
						"x": 1114,
						"y": 572,
						"width": 558,
						"height": 280
					}
				],
				"label": "A2_비듬_각질_상피성잔고리",
				"type": "box"
			}
		}
	]
}