{
	"metaData": {
		"Raw data ID": "IMG_C_A2_31_201673.jpg",
		"copyrighter": "㈜미소정보기술",
		"resolution": "1920X1080",
		"date": "2021-12-15",
		"breed": "러시안블루",
		"age": "10",
		"gender": "F",
		"region": "L",
		"camera type": "IMG",
		"species": "C",
		"lesions": "A2",
		"diagnosis": "",
		"Path": "유증상",
		"identifier": "피부질환",
		"src_path": "/라벨링데이터/반려묘/피부/일반카메라/유증상/A2_비듬_각질_상피성잔고리",
		"label_path": "/라벨링데이터/반려묘/피부/일반카메라/유증상/A2_비듬_각질_상피성잔고리",
		"type": "json",
		"fileformat": "jpg"
	},
	"inspRejectYn": "N",
	"labelingInfo": [
		{
			"polygon": {
				"color": "#1beaac",
				"location": [
					{
						"x1": 1398,
						"y1": 438,
						"x2": 1445,
						"y2": 458,
						"x3": 1488,
						"y3": 465,
						"x4": 1519,
						"y4": 455,
						"x5": 1528,
						"y5": 431,
						"x6": 1512,
						"y6": 399,
						"x7": 1459,
						"y7": 363,
						"x8": 1427,
						"y8": 339,
						"x9": 1394,
						"y9": 324,
						"x10": 1357,
						"y10": 313,
						"x11": 1328,
						"y11": 303,
						"x12": 1292,
						"y12": 297,
						"x13": 1247,
						"y13": 292,
						"x14": 1204,
						"y14": 292,
						"x15": 1175,
						"y15": 302,
						"x16": 1162,
						"y16": 313,
						"x17": 1159,
						"y17": 325,
						"x18": 1168,
						"y18": 351,
						"x19": 1201,
						"y19": 376,
						"x20": 1214,
						"y20": 381,
						"x21": 1398,
						"y21": 438
					}
				],
				"label": "A2_비듬_각질_상피성잔고리",
				"type": "polygon"
			}
		},
		{
			"box": {
				"color": "#1beaac",
				"location": [
					{
						"x": 1159,
						"y": 292,
						"width": 369,
						"height": 173
					}
				],
				"label": "A2_비듬_각질_상피성잔고리",
				"type": "box"
			}
		}
	]
}