{
	"metaData": {
		"Raw data ID": "IMG_C_A2_22_202423.jpg",
		"copyrighter": "㈜미소정보기술",
		"resolution": "1920X1080",
		"date": "2021-12-15",
		"breed": "코리안숏헤어",
		"age": "10",
		"gender": "F",
		"region": "L",
		"camera type": "IMG",
		"species": "C",
		"lesions": "A2",
		"diagnosis": "",
		"Path": "유증상",
		"identifier": "피부질환",
		"src_path": "/라벨링데이터/반려묘/피부/일반카메라/유증상/A2_비듬_각질_상피성잔고리",
		"label_path": "/라벨링데이터/반려묘/피부/일반카메라/유증상/A2_비듬_각질_상피성잔고리",
		"type": "json",
		"fileformat": "jpg"
	},
	"inspRejectYn": "N",
	"labelingInfo": [
		{
			"polygon": {
				"color": "#1beaac",
				"location": [
					{
						"x1": 453,
						"y1": 406,
						"x2": 393,
						"y2": 391,
						"x3": 281,
						"y3": 389,
						"x4": 197,
						"y4": 389,
						"x5": 157,
						"y5": 399,
						"x6": 130,
						"y6": 428,
						"x7": 122,
						"y7": 488,
						"x8": 122,
						"y8": 573,
						"x9": 130,
						"y9": 617,
						"x10": 182,
						"y10": 622,
						"x11": 234,
						"y11": 580,
						"x12": 279,
						"y12": 553,
						"x13": 341,
						"y13": 523,
						"x14": 430,
						"y14": 520,
						"x15": 467,
						"y15": 520,
						"x16": 485,
						"y16": 510,
						"x17": 490,
						"y17": 466,
						"x18": 453,
						"y18": 406
					}
				],
				"label": "A2_비듬_각질_상피성잔고리",
				"type": "polygon"
			}
		},
		{
			"box": {
				"color": "#1beaac",
				"location": [
					{
						"x": 122,
						"y": 389,
						"width": 368,
						"height": 233
					}
				],
				"label": "A2_비듬_각질_상피성잔고리",
				"type": "box"
			}
		}
	]
}