{
	"metaData": {
		"Raw data ID": "IMG_C_A2_202310.jpg",
		"copyrighter": "㈜미소정보기술",
		"resolution": "1920X1080",
		"date": "2021-12-15",
		"breed": "스코티쉬폴드",
		"age": "10",
		"gender": "M",
		"region": "B",
		"camera type": "IMG",
		"species": "C",
		"lesions": "A2",
		"diagnosis": "",
		"Path": "유증상",
		"identifier": "피부질환",
		"src_path": "/라벨링데이터/반려묘/피부/일반카메라/유증상/A2_비듬_각질_상피성잔고리",
		"label_path": "/라벨링데이터/반려묘/피부/일반카메라/유증상/A2_비듬_각질_상피성잔고리",
		"type": "json",
		"fileformat": "jpg"
	},
	"inspRejectYn": "N",
	"labelingInfo": [
		{
			"polygon": {
				"color": "#1beaac",
				"location": [
					{
						"x1": 1118,
						"y1": 645,
						"x2": 1144,
						"y2": 617,
						"x3": 1163,
						"y3": 581,
						"x4": 1138,
						"y4": 543,
						"x5": 1101,
						"y5": 515,
						"x6": 1033,
						"y6": 504,
						"x7": 969,
						"y7": 527,
						"x8": 927,
						"y8": 546,
						"x9": 893,
						"y9": 560,
						"x10": 864,
						"y10": 560,
						"x11": 843,
						"y11": 568,
						"x12": 818,
						"y12": 602,
						"x13": 824,
						"y13": 636,
						"x14": 854,
						"y14": 655,
						"x15": 924,
						"y15": 657,
						"x16": 994,
						"y16": 640,
						"x17": 1021,
						"y17": 637,
						"x18": 1056,
						"y18": 632,
						"x19": 1118,
						"y19": 645
					}
				],
				"label": "A2_비듬_각질_상피성잔고리",
				"type": "polygon"
			}
		},
		{
			"box": {
				"color": "#1beaac",
				"location": [
					{
						"x": 818,
						"y": 504,
						"width": 345,
						"height": 153
					}
				],
				"label": "A2_비듬_각질_상피성잔고리",
				"type": "box"
			}
		}
	]
}