{
	"metaData": {
		"Raw data ID": "IMG_C_A2_201650.jpg",
		"copyrighter": "㈜미소정보기술",
		"resolution": "1920X1080",
		"date": "2021-12-15",
		"breed": "코리안숏헤어",
		"age": "6",
		"gender": "F",
		"region": "H",
		"camera type": "IMG",
		"species": "C",
		"lesions": "A2",
		"diagnosis": "",
		"Path": "유증상",
		"identifier": "피부질환",
		"src_path": "/라벨링데이터/반려묘/피부/일반카메라/유증상/A2_비듬_각질_상피성잔고리",
		"label_path": "/라벨링데이터/반려묘/피부/일반카메라/유증상/A2_비듬_각질_상피성잔고리",
		"type": "json",
		"fileformat": "jpg"
	},
	"inspRejectYn": "N",
	"labelingInfo": [
		{
			"polygon": {
				"color": "#1beaac",
				"location": [
					{
						"x1": 1461,
						"y1": 560,
						"x2": 1458,
						"y2": 551,
						"x3": 1457,
						"y3": 547,
						"x4": 1459,
						"y4": 550,
						"x5": 1454,
						"y5": 539,
						"x6": 1452,
						"y6": 533,
						"x7": 1447,
						"y7": 522,
						"x8": 1445,
						"y8": 512,
						"x9": 1444,
						"y9": 499,
						"x10": 1443,
						"y10": 488,
						"x11": 1442,
						"y11": 482,
						"x12": 1440,
						"y12": 480,
						"x13": 1443,
						"y13": 482,
						"x14": 1436,
						"y14": 477,
						"x15": 1429,
						"y15": 475,
						"x16": 1422,
						"y16": 471,
						"x17": 1413,
						"y17": 468,
						"x18": 1401,
						"y18": 467,
						"x19": 1389,
						"y19": 466,
						"x20": 1373,
						"y20": 466,
						"x21": 1358,
						"y21": 466,
						"x22": 1350,
						"y22": 467,
						"x23": 1350,
						"y23": 467,
						"x24": 1353,
						"y24": 470,
						"x25": 1360,
						"y25": 475,
						"x26": 1370,
						"y26": 480,
						"x27": 1371,
						"y27": 482,
						"x28": 1371,
						"y28": 487,
						"x29": 1370,
						"y29": 494,
						"x30": 1370,
						"y30": 501,
						"x31": 1374,
						"y31": 508,
						"x32": 1383,
						"y32": 518,
						"x33": 1392,
						"y33": 524,
						"x34": 1400,
						"y34": 529,
						"x35": 1405,
						"y35": 524,
						"x36": 1406,
						"y36": 524,
						"x37": 1407,
						"y37": 526,
						"x38": 1410,
						"y38": 524,
						"x39": 1411,
						"y39": 526,
						"x40": 1422,
						"y40": 530,
						"x41": 1428,
						"y41": 536,
						"x42": 1436,
						"y42": 544,
						"x43": 1443,
						"y43": 551,
						"x44": 1452,
						"y44": 559,
						"x45": 1461,
						"y45": 560
					}
				],
				"label": "A2_비듬_각질_상피성잔고리",
				"type": "polygon"
			}
		},
		{
			"box": {
				"color": "#1beaac",
				"location": [
					{
						"x": 1350,
						"y": 466,
						"width": 111,
						"height": 94
					}
				],
				"label": "A2_비듬_각질_상피성잔고리",
				"type": "box"
			}
		}
	]
}